MANIFEST.in
README.rst
setup.py
doc/code.rst
doc/index.rst
doc/reference.rst
doc/qa/depend.rst
doc/qa/get.rst
doc/qa/underthehood.rst
doc/qa/usage.rst
doc/qa/what.rst
doc/qa/which.rst
doc/qa/workflows.rst
doc/tut/basic.rst
doc/tut/custom.rst
doc/tut/remote.rst
doc/tut/stochastic.rst
doc/tut/sub.rst
stosim/__init__.py
stosim/stosim
stosim.egg-info/PKG-INFO
stosim.egg-info/SOURCES.txt
stosim.egg-info/dependency_links.txt
stosim.egg-info/requires.txt
stosim.egg-info/top_level.txt
stosim/analysis/__init__.py
stosim/analysis/compressor.py
stosim/analysis/harvester.py
stosim/analysis/plotter.py
stosim/analysis/tester.py
stosim/sim/__init__.py
stosim/sim/commands.py
stosim/sim/job_creator.py
stosim/sim/utils.py