Metadata-Version: 1.1
Name: stosim
Version: 0.2.19
Summary: Stochastic Simulations
Home-page: http://homepages.cwi.nl/~nicolas/stosim/
Author: Nicolas Höning
Author-email: iam@nicolashoening.de
License: Apache Software License
Platform: Unix
Classifier: Programming Language :: Python :: 2.7
Classifier: Development Status :: 4 - Beta
Classifier: Natural Language :: English
Classifier: Environment :: Console
Classifier: Intended Audience :: Developers
Classifier: License :: OSI Approved :: Apache Software License
Classifier: Operating System :: POSIX
Classifier: Topic :: Software Development :: Libraries :: Python Modules
Classifier: Topic :: System :: Distributed Computing
Classifier: Topic :: Utilities
